{
	"id": "10d571a28620b0363f589e11f2b9575401d1b49d",
	"title": "Child Care and Early Years IT Modernization",
	"agency": "Government of Ontario",
	"status": "Open",
	"project_reference": "",
	"created_at": "25/09/2025 12:00",
	"category": "IT",
	"listing_expiry_date": "06/11/2025 11:00",
	"portal_url": "https://ontariotenders.app.jaggaer.com/esop/toolkit/opportunity/current/list.si",
	"region": "CA-ON",
	"city": "Ontario",
	"portal_source": "Ontario Tenders Portal",
	"hash_fingerprint": "10d571a28620b0363f589e11f2b9575401d1b49d"
}